ds365ai/__init__.py
DS365ai-0.1.0.dist-info/METADATA
DS365ai-0.1.0.dist-info/WHEEL
DS365ai-0.1.0.dist-info/top_level.txt
DS365ai-0.1.0.dist-info/RECORD
