Metadata-Version: 2.1
Name: DS365ai
Version: 0.1.0
Summary: A Python package for DS365ai
Home-page: 
Author: DS365ai
Author-email: 
Classifier: Programming Language :: Python :: 3
Classifier: License :: OSI Approved :: MIT License
Classifier: Operating System :: OS Independent
Requires-Python: >=3.6
